kre/__init__.py
kre/kre.py
kre/tools/__init__.py
kre/tools/_constants.py
kre/tools/_tools.py
kre-0.9.9.dist-info/LICENSE
kre-0.9.9.dist-info/METADATA
kre-0.9.9.dist-info/WHEEL
kre-0.9.9.dist-info/RECORD
