Metadata-Version: 2.1
Name: kre
Version: 0.9.9
Summary: Subcharacter-level regular expression functionality for Korean
Home-page: https://github.com/darrelllarsen/kre
License: GPL-3.0-only
Author: Darrell Larsen
Author-email: pythonkre@gmail.com
Requires-Python: >=3.7,<4.0
Classifier: Development Status :: 4 - Beta
Classifier: License :: OSI Approved :: GNU General Public License v3 (GPLv3)
Classifier: Natural Language :: Korean
Classifier: Operating System :: OS Independent
Classifier: Programming Language :: Python :: 3
Classifier: Programming Language :: Python :: 3.7
Classifier: Programming Language :: Python :: 3.8
Classifier: Programming Language :: Python :: 3.9
Classifier: Programming Language :: Python :: 3.10
Classifier: Programming Language :: Python :: 3.11
Classifier: Programming Language :: Python :: 3.12
Classifier: Topic :: Text Processing :: Linguistic
Classifier: Topic :: Utilities
Project-URL: Documentation, https://github.com/darrelllarsen/kre/wiki
Project-URL: Repository, https://github.com/darrelllarsen/kre
